playturtle/__init__.py
playturtle/__main__.py
playturtle/help_app.py
playturtle/playturtle.py
PlayTurtle-3.0.0.dist-info/LICENSE
PlayTurtle-3.0.0.dist-info/METADATA
PlayTurtle-3.0.0.dist-info/WHEEL
PlayTurtle-3.0.0.dist-info/entry_points.txt
PlayTurtle-3.0.0.dist-info/top_level.txt
PlayTurtle-3.0.0.dist-info/RECORD
