Metadata-Version: 2.1
Name: PlayTurtle
Version: 3.0.0
Summary: An application that provides a simplified way for children to learn programming
Author-email: Israel Waldner <imky171@gmail.com>
License: MIT License        
Project-URL: Homepage, https://github.com/mordy-python/PlayTurtle
Project-URL: Bug Tracker, https://github.com/mordy-python/PlayTurtle/issues
Keywords: python,turtle,learn-python
Classifier: Programming Language :: Python :: 3
Classifier: Development Status :: 4 - Beta
Classifier: Intended Audience :: End Users/Desktop
Classifier: Intended Audience :: Education
Classifier: License :: OSI Approved :: MIT License
Classifier: Operating System :: OS Independent
Classifier: Topic :: Education
Classifier: Topic :: Education :: Computer Aided Instruction (CAI)
Requires-Python: >=3.7
License-File: LICENSE
